{
  "geoblacklight_version": "1.0",
  "dc_identifier_s": "https://hgl.harvard.edu/catalog/harvard-g3764-b6p1-2000-m4",
  "dc_title_s": "Public Transit Map, Massachusetts, ca. 2000 (Raster Image)",
  "dc_description_s": "This layer is a georeferenced raster image of the historic paper map entitled: Official public transit map :[Boston and vicinity, Massachusetts] : Massachusetts Bay Transportation Authority / this map was prepared for the MBTA by the Central Transportation Planning Staff ; cartography by Kenneth A. Dumas, CTPS ; production by Transportation Creative Services. It was published by Massachusetts Bay Transportation Authority ca. 2000. Scale 1:21,120. 1 in. = 1/3 of a mile. The image inside the map neatline is georeferenced to the surface of the earth and fit to the Massachusetts State Plane Coordinate System, Mainland Zone (in Feet) (Fipszone 2001). All map collar and inset information is also available as part of the raster image, including any inset maps, profiles, statistical tables, directories, text, illustrations, index maps, legends, or other information associated with the principal map. This map shows features such as roads, railroads, drainage, cities and other human settlements, territorial boundaries, shoreline features, and more. Includes also general information on bus, subway, rail, and boat transportation, service frequencies in minutes for bus routes and subway lines, inset of 'MBTA commuter rail system,' inset showing transportational services for Lynn, Salem, Beverly, and vicinity, 18 insets showing transportational services for locales at or near stations, advertisement, manuscript annotations and color illustrations. This layer is part of a selection of digitally scanned and georeferenced historic maps from the Harvard Map Collection. These maps typically portray both natural and manmade features. The selection represents a range of originators, ground condition dates, scales, and map purposes.",
  "dc_rights_s": "Public",
  "dct_provenance_s": "Harvard",
  "dct_references_s": "{\"http://www.opengis.net/cat/csw/csdgm\":\"https://raw.githubusercontent.com/harvard-library/harvard-geodata/main/fgdc/G3764_B6P1_2000_M4.xml\",\"http://www.opengis.net/def/serviceType/ogc/wms\":\"https://geodata-proxy.lib.harvard.edu/geoserver/proxy/requestfile/wms\",\"http://www.opengis.net/def/serviceType/ogc/wfs\":\"https://geodata-proxy.lib.harvard.edu/geoserver/proxy/requestfile/wfs\",\"http://schema.org/DownloadAction\":\"https://geodata-proxy.lib.harvard.edu/geoserver/proxy/downloadfile\"}",
  "layer_id_s": "mapimages_public:G3764_B6P1_2000_M4",
  "layer_slug_s": "harvard-g3764-b6p1-2000-m4",
  "layer_geom_type_s": "Raster",
  "layer_modified_dt": "2013-12-05T00:00:00Z",
  "dc_creator_sm": [
    "Harvard Map Collection, Harvard Library",
    "Metropolitan Planning Organization (Mass.). Central Transportation Planning                    Staff.",
    "Dumas, Kenneth A.",
    "Transportation Creative Services (Firm)",
    "Massachusetts Bay Transportation Authority."
  ],
  "dc_publisher_s": [
    "Harvard Map Collection, Harvard Library"
  ],
  "dc_format_s": "GeoTIFF",
  "dc_type_s": "Dataset",
  "dc_subject_sm": [
    "Maps",
    "Zoning",
    "Human settlements",
    "Cities and towns",
    "Villages",
    "Landforms",
    "Bodies of water",
    "Land use",
    "Infrastructure (Economics)",
    "Transportation",
    "imageryBaseMapsEarthCover",
    "transportation"
  ],
  "dct_spatial_sm": [
    "Massachusetts"
  ],
  "dct_issued_s": "2013-11",
  "dct_temporal_sm": [
    "2000"
  ],
  "solr_geom": "ENVELOPE(-71.736635, -70.235316, 42.816788, 41.938233)",
  "solr_year_i": 2000,
  "harvard_collectionID_sm": [
    "9886703"
  ]
}