<?xml version="1.0" encoding="UTF-8"?>
<metadata>
  <idinfo>
    <citation>
      <citeinfo>
        <origin>City of Newton GIS</origin>
        <pubdate>1998?</pubdate>
        <title>Storm Water Collection System Points - City of Newton</title>
        <geoform>vector digital data</geoform>
        <onlink>https://hgl.harvard.edu/catalog/harvard-nwtndrainpt</onlink>
      </citeinfo>
    </citation>
    <descript>
      <abstract>This coverage contains point features such as manholes, catchbasins, ditch ends, dry wells, pipe junctions, pipe ends and outfalls which comprise part of the storm water collection network for the city of Newton.
Line features such as pipes and ditches are contained in the Storm Water Collection System Lines data layer.</abstract>
      <purpose>This layer is intended for researchers, students, and policy makers and planners for reference and mapping purposes, and may be used for basic applications such as viewing, querying, and map output production, or to provide a basemap to support graphical overlays and analysis with other spatial data.

This layer may provide a basemap for layers related to urban planning, public works, or utilities purposes (including defining boundaries, managing assets and facilities, integrating attribute databases with geographic features, spatial analysis, and presentation output.</purpose>
      <supplinf>This data layer is not presently being maintained; however, the Department of Public Works is attempting to start a project to field check the drain infrastructure and resolve some of the many discrepancies.</supplinf>
    </descript>
    <timeperd>
      <timeinfo>
        <sngdate>
          <caldate>1998?</caldate>
        </sngdate>
      </timeinfo>
      <current>ground condition</current>
    </timeperd>
    <status>
      <progress>Complete</progress>
      <update>As needed</update>
    </status>
    <spdom>
      <bounding>
        <westbc>-71.268230</westbc>
        <eastbc>-71.157366</eastbc>
        <northbc>42.367306</northbc>
        <southbc>42.287818</southbc>
      </bounding>
    </spdom>
    <keywords>
      <theme>
        <themekt>ISO 19115 Topic Category</themekt>
        <themekey>utilitiesCommunication</themekey>
      </theme>
      <theme>
        <themekt>HGL Category Keyword Thesaurus</themekt>
        <themekey>Municipal</themekey>
      </theme>
      <theme>
        <themekt>LCSH</themekt>
        <themekey>Catchments</themekey>
        <themekey>Storm sewers</themekey>
        <themekey>Runoff</themekey>
        <themekey>Manholes</themekey>
        <themekey>Municipal engineering</themekey>
      </theme>
      <place>
        <placekt>GNIS</placekt>
        <placekey>Newton</placekey>
        <placekey>Massachusetts</placekey>
      </place>
    </keywords>
    <accconst>Access is granted to licensee (Harvard University) only. Available only to Harvard University affiliates.</accconst>
    <useconst>For educational or non-commercial use only.</useconst>
    <ptcontac>
      <cntinfo>
        <cntorgp>
          <cntorg>City of Newton GIS</cntorg>
        </cntorgp>
        <cntpos>GIS Administrator</cntpos>
        <cntaddr>
          <addrtype>mailing and physical address</addrtype>
          <address>Information Technology Department</address>
          <address>City Hall  Room 107</address>
          <address>1000 Commonwealth Avenue</address>
          <city>Newton Center</city>
          <state>MA</state>
          <postal>02459-1400</postal>
          <country>USA</country>
        </cntaddr>
        <cntvoice>617-796-1180</cntvoice>
        <cntvoice>617-796-1000</cntvoice>
      </cntinfo>
    </ptcontac>
    <datacred>GIS data supplied by City of Newton GIS.</datacred>
    <secinfo>
      <secclass>Unclassified</secclass>
    </secinfo>
    <native>Microsoft Windows NT Version 4.0 (Build 1381) Service Pack 6; ESRI ArcCatalog 8.2.0.700</native>
  </idinfo>
  <dataqual>
    <attracc/>
    <logic>This data layer is known to contain errors in content and in the connections between features.  This data layer should be regarded as a draft and other sources, specifically the as-built construction drawings, should be consulted as appropriate.</logic>
    <posacc>
      <horizpa>
        <horizpar>Manhole and catch basin locations mapped based on photogrammetric locations have an absolute accuracy of +/- 2.5 feet.  The accuracy of the other manhole and catch basin locations is unknown.  The accuracy of the pipe features is unknown.</horizpar>
      </horizpa>
    </posacc>
    <lineage>
      <srcinfo>
        <srccite>
          <citeinfo>
            <origin>James W. Sewall Co.</origin>
            <title>James W. Sewall Co. Aerial Photography</title>
          </citeinfo>
        </srccite>
        <srcscale>7200</srcscale>
        <typesrc>stable-base material</typesrc>
        <srctime>
          <timeinfo>
            <sngdate>
              <caldate>19940415</caldate>
            </sngdate>
          </timeinfo>
          <srccurr>ground condition</srccurr>
        </srctime>
        <srccitea>Sewall94</srccitea>
        <srccontr>Mapping of water/sewer/drain infrastructure based on targets painted on the streets, conducted by the James W. Sewall Co. The aerial photographs were taken on April 15, 1994.  The photographs were produced at a scale of 1" = 600' at an approximate altitude above datum of 3,600 feet.
The information below is from the J. W. Sewall Co. Proposal Documents
Scale of Photography: 1:7200
Forward Overlap: 60% average within 5 feet.
Side Overlap: 30% average within 10 feet
Tilt: Not to exceed 3 degrees - 4 degrees between flight lines
Crab: Not to exceed 3 degrees relative to flight line
Contact Prints: 9" x 9" received from company.
Ground Control: Primary - 12 permanent control markers set - 36" concrete monuments. GPS network of 50 stations with three horizontal and nine vertical ties to grid. Network tied to MSPCS NAD83 datum and NGVD29 datum by occupying Mass. Highway Department control points.
Block Adjustment Accuracy: Horizontal: second order class I; Vertical: third order 
Model: ALBANY-Lite
Final Pixel Size: 12 inches
Final Horizontal Accuracy: Approximately +/- 5 feet.</srccontr>
      </srcinfo>
      <srcinfo>
        <srccite>
          <citeinfo>
            <origin>Newton Department of Public Works</origin>
            <pubdate>Unknown</pubdate>
            <title>Atlas Maps</title>
          </citeinfo>
        </srccite>
        <srcscale>4800</srcscale>
        <typesrc>paper</typesrc>
        <srctime>
          <timeinfo>
            <sngdate>
              <caldate>unknown</caldate>
            </sngdate>
          </timeinfo>
          <srccurr>ground condition</srccurr>
        </srctime>
        <srccitea>ATLAS</srccitea>
        <srccontr>Construction drawing ID's were taken from the existing atlas maps and added as an attribute of drain pipe segments</srccontr>
      </srcinfo>
      <procstep>
        <procdesc>Storm drain manholes and catch basins were photogrammetrically captured from the aerial photography referred to in the introduction to this document.  A field check of the area of four 1" = 40' scale Assessor's sheets showed that the capture rates for manholes and catch basins were, respectively, 95% and 90% correct.  The figures for the manholes are, however, somewhat misleading.  This is because at the time of the photography, the city was known to have instances of sewer manhole lids on storm drain manholes, and vice versa.

Data layer development was completed under contract with Applied Geographics, Inc. (AGI) of Boston.  AGI was provided two kinds of source information:
1) The existing 1" = 400' scale atlas maps.
2) Storm drain catch basins and manhole locations mapped photogrammetrically from aerial photography taken in April 1994.

This data layer was created "on screen" with a back-drop of the point features from the aerial photography and other appropriate features from the city's GIS database (e.g., street rights-of-way).  The contractor's staff then constructed the storm drain network while referencing both the on-screen features and features from the paper atlas.  Construction drawing ID's were taken from the existing atlas maps and added as an attribute of drain pipe segments. This data layer is sufficient in most cases for providing a general idea as to the locations of these features on the ground.</procdesc>
        <procdate>Unknown</procdate>
        <proccont>
          <cntinfo>
            <cntorgp>
              <cntorg>Newton GIS</cntorg>
            </cntorgp>
          </cntinfo>
        </proccont>
      </procstep>
      <procstep>
        <procdesc>The original shape file was imported to an ArcSDE Layer.</procdesc>
        <procdate>200208</procdate>
        <proccont>
          <cntinfo>
            <cntorgp>
              <cntorg>Harvard Geospatial Library Team</cntorg>
            </cntorgp>
            <cntaddr>
              <addrtype>mailing and physical address</addrtype>
              <address>Office of Information Systems</address>
              <address>1280 Massachusetts Avenue</address>
              <city>Cambridge</city>
              <state>MA</state>
              <postal>02138</postal>
              <country>USA</country>
            </cntaddr>
            <cntvoice>617-495-2417</cntvoice>
            <cntfax>617-496-0440</cntfax>
            <cntemail>hgl_ref@hulmail.harvard.edu</cntemail>
          </cntinfo>
        </proccont>
      </procstep>
      <procstep>
        <procdesc>Metadata created, imported and edited</procdesc>
        <procdate>20021002</procdate>
        <proccont>
          <cntinfo>
            <cntorgp>
              <cntorg>Harvard Geospatial Library</cntorg>
              <cntper>Geospatial Resources Cataloger</cntper>
            </cntorgp>
            <cntvoice>617-495-2417</cntvoice>
            <cntfax>617-496-0440</cntfax>
          </cntinfo>
        </proccont>
      </procstep>
    </lineage>
  </dataqual>
  <spdoinfo>
    <direct>Vector</direct>
    <ptvctinf>
      <sdtsterm>
        <sdtstype>Entity point</sdtstype>
        <ptvctcnt>22529</ptvctcnt>
      </sdtsterm>
    </ptvctinf>
  </spdoinfo>
  <spref>
    <horizsys>
      <planar>
        <gridsys>
          <gridsysn>State Plane Coordinate System</gridsysn>
          <spcs>
            <spcszone>2001</spcszone>
            <lambertc>
              <stdparll>41.716667</stdparll>
              <stdparll>42.683333</stdparll>
              <longcm>-71.500000</longcm>
              <latprjo>41.000000</latprjo>
              <feast>656166.666667</feast>
              <fnorth>2460625.000000</fnorth>
            </lambertc>
          </spcs>
        </gridsys>
        <planci>
          <plance>coordinate pair</plance>
          <coordrep>
            <absres>0.000015</absres>
            <ordres>0.000015</ordres>
          </coordrep>
          <plandu>survey feet</plandu>
        </planci>
      </planar>
      <geodetic>
        <horizdn>North American Datum of 1983</horizdn>
        <ellips>Geodetic Reference System 80</ellips>
        <semiaxis>6378137.000000</semiaxis>
        <denflat>298.257222</denflat>
      </geodetic>
    </horizsys>
    <vertdef>
      <altsys>
        <altdatum>National Geodetic Vertical Datum of 1929</altdatum>
        <altres>1.000000</altres>
        <altenc>Explicit elevation coordinate included with horizontal coordinates</altenc>
      </altsys>
    </vertdef>
  </spref>
  <eainfo>
    <detailed>
      <enttyp>
        <enttypl>Storm Water Collection Points</enttypl>
        <enttypd>ESRI Shapefile. Points represent water system features</enttypd>
        <enttypds>ESRI, Newton GIS</enttypds>
      </enttyp>
      <attr>
        <attrlabl>ARC_</attrlabl>
        <attrdef>Internal Feature Identifier</attrdef>
        <attrdefs>ESRI</attrdefs>
      </attr>
      <attr>
        <attrlabl>DRAIN_</attrlabl>
        <attrdef>Internal Feature Identifier</attrdef>
        <attrdefs>ESRI</attrdefs>
      </attr>
      <attr>
        <attrlabl>DRAIN_ID</attrlabl>
        <attrdef>Internal Feature Identifier</attrdef>
        <attrdefs>ESRI</attrdefs>
      </attr>
      <attr>
        <attrlabl>TYPE</attrlabl>
        <attrdef>Type of node feature</attrdef>
        <attrdefs>Newton GIS</attrdefs>
        <attrdomv>
          <edom>
            <edomv>BLEED</edomv>
            <edomvd>Bleeder Valve</edomvd>
            <edomvds>Newton GIS</edomvds>
          </edom>
          <edom>
            <edomv>END</edomv>
            <edomvds>Newton GIS</edomvds>
          </edom>
          <edom>
            <edomv>CB</edomv>
            <edomvd>Catch Basin</edomvd>
            <edomvds>Newton GIS</edomvds>
          </edom>
          <edom>
            <edomv>DITCH END</edomv>
            <edomvds>Newton GIS</edomvds>
          </edom>
          <edom>
            <edomv>DRY WELL</edomv>
            <edomvds>Newton GIS</edomvds>
          </edom>
          <edom>
            <edomv>INTAKE</edomv>
            <edomvds>Newton GIS</edomvds>
          </edom>
          <edom>
            <edomv>JCT</edomv>
            <edomvd>Pipe junction</edomvd>
            <edomvds>Newton GIS</edomvds>
          </edom>
          <edom>
            <edomv>MH-D</edomv>
            <edomvd>Manhole</edomvd>
            <edomvds>Newton GIS</edomvds>
          </edom>
          <edom>
            <edomv>OUTFALL</edomv>
            <edomvds>Newton GIS</edomvds>
          </edom>
          <edom>
            <edomv>PIPE END</edomv>
            <edomvds>Newton GIS</edomvds>
          </edom>
          <edom>
            <edomv>WC</edomv>
            <edomvd>Undefined. Only one feature of this type</edomvd>
            <edomvds>Newton GIS</edomvds>
          </edom>
        </attrdomv>
        <attrvai>
          <attrva>No explanation if they are self explanatory</attrva>
        </attrvai>
      </attr>
      <attr>
        <attrlabl>RELIABILIT</attrlabl>
        <attrdef>Indicates the reliability of the information given potentially conflicting or disagreeing sources</attrdef>
        <attrdefs>Newton GIS</attrdefs>
        <attrdomv>
          <edom>
            <edomv>MATCH</edomv>
            <edomvd>Photo source and atlas source agree</edomvd>
            <edomvds>Newton GIS</edomvds>
          </edom>
          <edom>
            <edomv>NOT IN ATLAS</edomv>
            <edomvd>Feature on the photo, but no match in the atlas</edomvd>
            <edomvds>Newton GIS</edomvds>
          </edom>
          <edom>
            <edomv>NOT ON PHOTOS</edomv>
            <edomvd>Feature appears in the atlas but was not mapped from the photos</edomvd>
            <edomvds>Newton GIS</edomvds>
          </edom>
        </attrdomv>
      </attr>
      <attr>
        <attrlabl>DIAM_CHANG</attrlabl>
        <attrdef>Indicates that the pipe diameter has changed at this node</attrdef>
        <attrdefs>Newton GIS</attrdefs>
      </attr>
      <attr>
        <attrlabl>EDIT_SOURC</attrlabl>
        <attrdef>Source of an edit to the feature</attrdef>
        <attrdefs>Newton GIS</attrdefs>
        <attrdomv>
          <edom>
            <edomv>WC</edomv>
            <edomvd>Woodard and Curran</edomvd>
            <edomvds>Newton GIS</edomvds>
          </edom>
          <edom>
            <edomv>AB</edomv>
            <edomvd>As build drawing</edomvd>
            <edomvds>Newton GIS</edomvds>
          </edom>
        </attrdomv>
      </attr>
      <attr>
        <attrlabl>MANHOLE_ID</attrlabl>
        <attrdef>Manhole unique identifier</attrdef>
        <attrdefs>Newton GIS</attrdefs>
      </attr>
      <attr>
        <attrlabl>OUTFALL_ID</attrlabl>
        <attrdef>The numeric identifier of the storm drain sub-basin that drains to the river through the outfall.</attrdef>
        <attrdefs>Newton GIS</attrdefs>
      </attr>
      <attr>
        <attrlabl>NWTNDRAINPT.FID</attrlabl>
        <attrdef>Internal feature number.</attrdef>
        <attrdefs>ESRI</attrdefs>
        <attrdomv>
          <udom>Sequential unique whole numbers that are automatically generated.</udom>
        </attrdomv>
      </attr>
      <attr>
        <attrlabl>SHAPE</attrlabl>
        <attrdef>Feature geometry.</attrdef>
        <attrdefs>ESRI</attrdefs>
        <attrdomv>
          <udom>Coordinates defining the features.</udom>
        </attrdomv>
      </attr>
    </detailed>
  </eainfo>
  <distinfo>
    <distrib>
      <cntinfo>
        <cntorgp>
          <cntorg>Harvard Geospatial Library</cntorg>
        </cntorgp>
        <cntaddr>
          <addrtype>mailing and physical address</addrtype>
          <address>Office of Information Systems</address>
          <address>1280 Massachusetts Avenue</address>
          <city>Cambridge</city>
          <state>MA</state>
          <postal>02138</postal>
          <country>USA</country>
        </cntaddr>
        <cntvoice>617-495-2417</cntvoice>
        <cntfax>617-496-0440</cntfax>
        <cntemail>hgl_ref@hulmail.harvard.edu</cntemail>
        <hours>Monday - Friday, 9:00 am - 4:00 pm EST</hours>
      </cntinfo>
    </distrib>
    <resdesc>Downloadable Data</resdesc>
    <stdorder>
      <digform>
        <digtinfo>
          <formname>Shape</formname>
          <filedec>Zip</filedec>
        </digtinfo>
      </digform>
      <fees>None</fees>
      <ordering>Web based distribution only. http://hgl.harvard.edu</ordering>
    </stdorder>
  </distinfo>
  <metainfo>
    <metd>20021011</metd>
    <metc>
      <cntinfo>
        <cntorgp>
          <cntorg>Harvard Geospatial Library</cntorg>
          <cntper>Geospatial Resources Cataloger</cntper>
        </cntorgp>
        <cntaddr>
          <addrtype>mailing and physical address</addrtype>
          <address>Office of Information Systems</address>
          <address>1280 Massachusetts Avenue</address>
          <city>Cambridge</city>
          <state>MA</state>
          <postal>02138</postal>
          <country>USA</country>
        </cntaddr>
        <cntvoice>617-295-12417</cntvoice>
        <cntfax>617-496-0440</cntfax>
        <cntemail>hgl_ref@hulmail.harvard.edu</cntemail>
      </cntinfo>
    </metc>
    <metstdn>FGDC Content Standards for Digital Geospatial Metadata</metstdn>
    <metstdv>FGDC-STD-001-1998</metstdv>
    <mettc>local time</mettc>
    <metsi>
      <metsc>Unclassified</metsc>
    </metsi>
    <metextns>
      <onlink>http://www.esri.com/metadata/esriprof80.html</onlink>
      <metprof>ESRI Metadata Profile</metprof>
    </metextns>
  </metainfo>
</metadata>
